huddu/Queue.py
huddu/Store.py
huddu/__init__.py
huddu/_exceptions.py
huddu/_sessions.py
huddu/utils.py
huddu-1.1.13.dist-info/LICENSE
huddu-1.1.13.dist-info/METADATA
huddu-1.1.13.dist-info/WHEEL
huddu-1.1.13.dist-info/top_level.txt
huddu-1.1.13.dist-info/RECORD
