Metadata-Version: 2.1
Name: huddu
Version: 1.1.13
Summary: Python SDK for Huddu
Home-page: https://github.com/hudduapp/huddu-python
Author: Joshua3212
Author-email: hello@huddu.io
License: MIT
Platform: UNKNOWN
Requires: json
Requires: requests
Requires: pyjwt
License-File: LICENSE
